musicnn/__init__.py
musicnn/configuration.py
musicnn/extractor.py
musicnn/models.py
musicnn/tagger.py
musicnn/MSD_musicnn/.data-00000-of-00001
musicnn/MSD_musicnn/.index
musicnn/MSD_musicnn/.meta
musicnn/MSD_musicnn/checkpoint
musicnn/MSD_musicnn/config.json
musicnn/MSD_musicnn/experiment.result
musicnn/MSD_musicnn/train_log.tsv
musicnn/MSD_vgg/.data-00000-of-00001
musicnn/MSD_vgg/.index
musicnn/MSD_vgg/.meta
musicnn/MSD_vgg/checkpoint
musicnn/MSD_vgg/config.json
musicnn/MSD_vgg/experiment.result
musicnn/MSD_vgg/train_log.tsv
musicnn/MTT_musicnn/.data-00000-of-00001
musicnn/MTT_musicnn/.index
musicnn/MTT_musicnn/.meta
musicnn/MTT_musicnn/checkpoint
musicnn/MTT_musicnn/config.json
musicnn/MTT_musicnn/experiment.result
musicnn/MTT_musicnn/train_log.tsv
musicnn/MTT_vgg/.data-00000-of-00001
musicnn/MTT_vgg/.index
musicnn/MTT_vgg/.meta
musicnn/MTT_vgg/checkpoint
musicnn/MTT_vgg/config.json
musicnn/MTT_vgg/experiment.result
musicnn/MTT_vgg/train_log.tsv
musicnn-0.1.0.dist-info/LICENSE.md
musicnn-0.1.0.dist-info/METADATA
musicnn-0.1.0.dist-info/WHEEL
musicnn-0.1.0.dist-info/top_level.txt
musicnn-0.1.0.dist-info/RECORD
