Metadata-Version: 2.1
Name: musicnn
Version: 0.1.0
Summary: Pronounced as "musician", musicnn is a set of pre-trained deep convolutional neural networks for music audio tagging
Home-page: http://github.com/jordipons/musicnn
Author: Jordi Pons
License: ISC
Keywords: audio music deep learning tagging tensorflow machine listening
Platform: UNKNOWN
Classifier: License :: OSI Approved :: ISC License (ISCL)
Classifier: Programming Language :: Python
Classifier: Development Status :: 3 - Alpha
Classifier: Intended Audience :: Developers
Classifier: Intended Audience :: Science/Research
Classifier: Topic :: Multimedia :: Sound/Audio :: Analysis
Classifier: Programming Language :: Python :: 3
Classifier: Programming Language :: Python :: 3.7
Requires-Dist: librosa (>=0.7.0)
Requires-Dist: tensorflow (>=1.14)
Requires-Dist: numpy (<1.17,>=1.14.5)
